card_live_dashboard/__init__.py
card_live_dashboard/app.py
card_live_dashboard/routes.py
card_live_dashboard/assets/dashboard.css
card_live_dashboard/assets/favicon.ico
card_live_dashboard/callbacks/__init__.py
card_live_dashboard/layouts/__init__.py
card_live_dashboard/layouts/figures.py
card_live_dashboard/model/CardLiveData.py
card_live_dashboard/model/GeographicSummaries.py
card_live_dashboard/model/RGIParser.py
card_live_dashboard/model/__init__.py
card_live_dashboard/model/data_modifiers/AddGeographicNamesModifier.py
card_live_dashboard/model/data_modifiers/AddTaxonomyModifier.py
card_live_dashboard/model/data_modifiers/AntarcticaNAModifier.py
card_live_dashboard/model/data_modifiers/CardLiveDataModifier.py
card_live_dashboard/model/data_modifiers/__init__.py
card_live_dashboard/service/CardLiveDataLoader.py
card_live_dashboard/service/CardLiveDataManager.py
card_live_dashboard/service/ConfigManager.py
card_live_dashboard/service/GeographicRegionCodesService.py
card_live_dashboard/service/TaxonomicParser.py
card_live_dashboard/service/__init__.py
card_live_dashboard/service/config/cardlive.yaml
card_live_dashboard/service/config/gunicorn.conf.py
card_live_dashboard/service/data/UN-M49/README.md
card_live_dashboard/service/data/UN-M49/UNSD-Methodology.csv
card_live_dashboard/test/__init__.py
card_live_dashboard/test/unit/__init__.py
card_live_dashboard/test/unit/model/__init__.py
card_live_dashboard/test/unit/model/test_CardLiveData.py
card_live_dashboard/test/unit/model/test_RGIParser.py
card_live_dashboard/test/unit/service/__init__.py
card_live_dashboard/test/unit/service/test_CardLiveDataLoader.py
card_live_dashboard/test/unit/service/test_GeographicRegionCodesService.py
card_live_dashboard/test/unit/service/test_TaxonomicParser.py
card_live_dashboard/test/unit/service/data/data1/file1
card_live_dashboard/test/unit/service/data/data2/file1
card_live_dashboard/test/unit/service/data/data2/file2
card_live_dashboard/test/unit/service/data/data3/file-invalid
card_live_dashboard-0.6.0.dist-info/LICENSE
card_live_dashboard-0.6.0.dist-info/METADATA
card_live_dashboard-0.6.0.dist-info/WHEEL
card_live_dashboard-0.6.0.dist-info/top_level.txt
card_live_dashboard-0.6.0.dist-info/RECORD
