Metadata-Version: 2.1
Name: card-live-dashboard
Version: 0.6.0
Summary: A dashboard to display antimicrobial resistance data from CARD:Live
Home-page: https://github.com/arpcard/card-live-dashboard/
Author: Aaron Petkau
Author-email: aaron.petkau@gmail.com
License: Apache v2.0
Platform: UNKNOWN
Classifier: Development Status :: 4 - Beta
Classifier: Environment :: Web Environment
Classifier: License :: OSI Approved :: Apache Software License
Classifier: Intended Audience :: Science/Research
Classifier: Topic :: Scientific/Engineering
Classifier: Topic :: Scientific/Engineering :: Bio-Informatics
Classifier: Programming Language :: Python :: 3.7
Classifier: Programming Language :: Python :: 3.8
Classifier: Operating System :: POSIX :: Linux
Requires-Dist: ete3 (>=3.1.2)
Requires-Dist: apscheduler
Requires-Dist: pandas
Requires-Dist: geopandas
Requires-Dist: numpy
Requires-Dist: dash
Requires-Dist: upsetplot
Requires-Dist: flask
Requires-Dist: dash-bootstrap-components
Requires-Dist: plotly
Requires-Dist: shapely
Requires-Dist: gunicorn
Requires-Dist: pytest
Requires-Dist: pyyaml
Requires-Dist: requests
Requires-Dist: setproctitle
Requires-Dist: zipstream-new
